<?xml version='1.0' encoding='utf-8'?>
<!DOCTYPE hibernate-mapping PUBLIC
    "-//Hibernate/Hibernate Mapping DTD 3.0//EN"
    "http://www.hibernate.org/dtd/hibernate-mapping-3.0.dtd">
<hibernate-mapping>

    <class name="com.leqi.bean.AdminEntity" table="admin" schema="leqi">
        <id name="adminId">
            <column name="admin_id" sql-type="int(11)"/>
        </id>
        <property name="nickname">
            <column name="nickname" sql-type="text"/>
        </property>
    </class>
</hibernate-mapping>